mvp/__init__.py
mvp/config.py
mvp/extensions.py
mvp/hooks.py
mvp/integration.py
mvp/presets.py
mvp/renderglobals.py
mvp/renderlayers.py
mvp/resources/__init__.py
mvp/resources/dots-vertical.png
mvp/resources/half.png
mvp/resources/icon.png
mvp/resources/resolution.png
mvp/resources/style.css
mvp/ui/__init__.py
mvp/ui/forms.py
mvp/ui/ui.py
mvp/utils.py
mvp/vendor/__init__.py
mvp/vendor/psforms/__init__.py
mvp/vendor/psforms/controls.py
mvp/vendor/psforms/exc.py
mvp/vendor/psforms/fields.py
mvp/vendor/psforms/form.py
mvp/vendor/psforms/Qt.py
mvp/vendor/psforms/resource.py
mvp/vendor/psforms/style.css
mvp/vendor/psforms/utils.py
mvp/vendor/psforms/validators.py
mvp/vendor/psforms/widgets.py
mvp/vendor/Qt.py
mvp/viewport.py
mvp-0.9.3.dist-info/LICENSE
mvp-0.9.3.dist-info/WHEEL
mvp-0.9.3.dist-info/METADATA
mvp-0.9.3.dist-info/RECORD
